[
  {"id":1700000001,"assetId":"AST-2023-00001","dateOfPurchase":"15/04/2023","invoiceNumber":"INV-VEH-2023-001","invoiceDate":"15/04/2023","partyName":"Tata Motors Ltd","location":"Mumbai Office","fundType":"Local Funds","assetType":"Vehicles","amountBeforeGst":"850000","gstAmount":"153000","totalInvoiceValue":"1003000","quantity":1,"narration":"Tata Safari - Project field use"},
  {"id":1700000002,"assetId":"AST-2023-00002","dateOfPurchase":"10/06/2023","invoiceNumber":"INV-OE-2023-002","invoiceDate":"10/06/2023","partyName":"Canon India Pvt Ltd","location":"Delhi Hub","fundType":"FCRA Funds","assetType":"Office Equipment","amountBeforeGst":"45000","gstAmount":"8100","totalInvoiceValue":"53100","quantity":1,"narration":"Canon ImageRunner Advance photocopier"},
  {"id":1700000003,"assetId":"AST-2023-00003","dateOfPurchase":"20/07/2023","invoiceNumber":"INV-COMP-2023-003","invoiceDate":"20/07/2023","partyName":"Dell Technologies India","location":"Bengaluru Center","fundType":"FCRA Funds","assetType":"Computers","amountBeforeGst":"55000","gstAmount":"9900","totalInvoiceValue":"64900","quantity":1,"narration":"Dell Inspiron 15 laptop - Programme team"},
  {"id":1700000004,"assetId":"AST-2023-00004","dateOfPurchase":"20/07/2023","invoiceNumber":"INV-COMP-2023-003","invoiceDate":"20/07/2023","partyName":"Dell Technologies India","location":"Mumbai Office","fundType":"FCRA Funds","assetType":"Computers","amountBeforeGst":"55000","gstAmount":"9900","totalInvoiceValue":"64900","quantity":1,"narration":"Dell Inspiron 15 laptop - Programme team"},
  {"id":1700000005,"assetId":"AST-2023-00005","dateOfPurchase":"05/09/2023","invoiceNumber":"INV-VEH-2023-004","invoiceDate":"05/09/2023","partyName":"Mahindra & Mahindra Ltd","location":"Bengaluru Center","fundType":"Local Funds","assetType":"Vehicles","amountBeforeGst":"920000","gstAmount":"165600","totalInvoiceValue":"1085600","quantity":1,"narration":"Mahindra Bolero pickup - Field operations"},
  {"id":1700000006,"assetId":"AST-2023-00006","dateOfPurchase":"15/11/2023","invoiceNumber":"INV-OE-2023-005","invoiceDate":"15/11/2023","partyName":"Godrej & Boyce Mfg Co","location":"Delhi Hub","fundType":"Local Funds","assetType":"Office Equipment","amountBeforeGst":"32000","gstAmount":"5760","totalInvoiceValue":"37760","quantity":1,"narration":"Godrej steel almirah - Records storage"},
  {"id":1700000007,"assetId":"AST-2023-00007","dateOfPurchase":"28/02/2024","invoiceNumber":"INV-COMP-2023-006","invoiceDate":"28/02/2024","partyName":"HP India Sales Pvt Ltd","location":"Mumbai Office","fundType":"Local Funds","assetType":"Computers","amountBeforeGst":"68000","gstAmount":"12240","totalInvoiceValue":"80240","quantity":1,"narration":"HP EliteBook 840 G9 - Finance & Admin"},
  {"id":1700000008,"assetId":"AST-2024-00001","dateOfPurchase":"12/04/2024","invoiceNumber":"INV-VEH-2024-001","invoiceDate":"12/04/2024","partyName":"Maruti Suzuki India Ltd","location":"Mumbai Office","fundType":"Local Funds","assetType":"Vehicles","amountBeforeGst":"750000","gstAmount":"135000","totalInvoiceValue":"885000","quantity":1,"narration":"Maruti Ertiga - Staff transport"},
  {"id":1700000009,"assetId":"AST-2024-00002","dateOfPurchase":"25/05/2024","invoiceNumber":"INV-COMP-2024-002","invoiceDate":"25/05/2024","partyName":"Apple India Pvt Ltd","location":"Delhi Hub","fundType":"FCRA Funds","assetType":"Computers","amountBeforeGst":"120000","gstAmount":"21600","totalInvoiceValue":"141600","quantity":1,"narration":"MacBook Pro M3 - Executive use"},
  {"id":1700000010,"assetId":"AST-2024-00003","dateOfPurchase":"18/07/2024","invoiceNumber":"INV-OE-2024-003","invoiceDate":"18/07/2024","partyName":"Samsung India Electronics","location":"Bengaluru Center","fundType":"FCRA Funds","assetType":"Office Equipment","amountBeforeGst":"38000","gstAmount":"6840","totalInvoiceValue":"44840","quantity":1,"narration":"Samsung 55 inch Smart display board - Conference room"},
  {"id":1700000011,"assetId":"AST-2024-00004","dateOfPurchase":"03/09/2024","invoiceNumber":"INV-COMP-2024-004","invoiceDate":"03/09/2024","partyName":"Lenovo India Pvt Ltd","location":"Bengaluru Center","fundType":"Local Funds","assetType":"Computers","amountBeforeGst":"48500","gstAmount":"8730","totalInvoiceValue":"57230","quantity":1,"narration":"Lenovo ThinkPad E14 - Field coordinator"},
  {"id":1700000012,"assetId":"AST-2024-00005","dateOfPurchase":"22/10/2024","invoiceNumber":"INV-VEH-2024-005","invoiceDate":"22/10/2024","partyName":"Toyota Kirloskar Motors","location":"Mumbai Office","fundType":"FCRA Funds","assetType":"Vehicles","amountBeforeGst":"1250000","gstAmount":"225000","totalInvoiceValue":"1475000","quantity":1,"narration":"Toyota Innova Crysta - Senior management"},
  {"id":1700000013,"assetId":"AST-2024-00006","dateOfPurchase":"15/01/2025","invoiceNumber":"INV-OE-2025-006","invoiceDate":"15/01/2025","partyName":"Epson India Pvt Ltd","location":"Delhi Hub","fundType":"Local Funds","assetType":"Office Equipment","amountBeforeGst":"22000","gstAmount":"3960","totalInvoiceValue":"25960","quantity":1,"narration":"Epson L3210 multifunction printer"},
  {"id":1700000014,"assetId":"AST-2024-00007","dateOfPurchase":"20/03/2025","invoiceNumber":"INV-COMP-2025-007","invoiceDate":"20/03/2025","partyName":"Dell Technologies India","location":"Bengaluru Center","fundType":"FCRA Funds","assetType":"Computers","amountBeforeGst":"52000","gstAmount":"9360","totalInvoiceValue":"61360","quantity":1,"narration":"Dell OptiPlex 3000 desktop - Branch operations"},
  {"id":1700000015,"assetId":"AST-2025-00001","dateOfPurchase":"08/04/2025","invoiceNumber":"INV-VEH-2025-001","invoiceDate":"08/04/2025","partyName":"Tata Motors Ltd","location":"Mumbai Office","fundType":"Local Funds","assetType":"Vehicles","amountBeforeGst":"1450000","gstAmount":"261000","totalInvoiceValue":"1711000","quantity":1,"narration":"Tata Nexon EV - Green initiative fleet"},
  {"id":1700000016,"assetId":"AST-2025-00002","dateOfPurchase":"30/05/2025","invoiceNumber":"INV-COMP-2025-002","invoiceDate":"30/05/2025","partyName":"HP India Sales Pvt Ltd","location":"Delhi Hub","fundType":"FCRA Funds","assetType":"Computers","amountBeforeGst":"75000","gstAmount":"13500","totalInvoiceValue":"88500","quantity":1,"narration":"HP ZBook Firefly 14 G10 - Design team"},
  {"id":1700000017,"assetId":"AST-2025-00003","dateOfPurchase":"14/07/2025","invoiceNumber":"INV-OE-2025-003","invoiceDate":"14/07/2025","partyName":"LG Electronics India","location":"Bengaluru Center","fundType":"Local Funds","assetType":"Office Equipment","amountBeforeGst":"58000","gstAmount":"10440","totalInvoiceValue":"68440","quantity":1,"narration":"LG 4K projector - Training centre"},
  {"id":1700000018,"assetId":"AST-2025-00004","dateOfPurchase":"22/09/2025","invoiceNumber":"INV-COMP-2025-004","invoiceDate":"22/09/2025","partyName":"Lenovo India Pvt Ltd","location":"Delhi Hub","fundType":"FCRA Funds","assetType":"Computers","amountBeforeGst":"62000","gstAmount":"11160","totalInvoiceValue":"73160","quantity":1,"narration":"Lenovo ThinkPad X1 Carbon - Director field visits"},
  {"id":1700000019,"assetId":"AST-2025-00005","dateOfPurchase":"10/11/2025","invoiceNumber":"INV-VEH-2025-005","invoiceDate":"10/11/2025","partyName":"Mahindra & Mahindra Ltd","location":"Bengaluru Center","fundType":"Local Funds","assetType":"Vehicles","amountBeforeGst":"1100000","gstAmount":"198000","totalInvoiceValue":"1298000","quantity":1,"narration":"Mahindra XUV700 - South zone operations"},
  {"id":1700000020,"assetId":"AST-2025-00006","dateOfPurchase":"05/01/2026","invoiceNumber":"INV-OE-2026-006","invoiceDate":"05/01/2026","partyName":"Godrej & Boyce Mfg Co","location":"Mumbai Office","fundType":"Local Funds","assetType":"Office Equipment","amountBeforeGst":"85000","gstAmount":"15300","totalInvoiceValue":"100300","quantity":1,"narration":"Godrej workstation furniture set - HR department"}
]
